<game fecha="2019-08-27T00:00:00-04:00" fase="clasificatoria">
 <team name="Pinar del Rio" c="2" h="4" e="4">
  <runxining 1="1" 2="0" 3="0" 4="0" 5="0" 6="0" 7="1"></runxining>
  <batters>
   <player name="Juan Carlos SS" vb="3" r="0" h="0" double="0" triple="0" hr="0" rbi="0" error="1"></player>
   <player name="Reinier León CF" vb="2" r="0" h="0" double="0" triple="0" hr="0" rbi="0" error="0"></player>
   <player name="Lázaro Emilio Blanco 1B,RF" vb="3" r="1" h="1" double="0" triple="0" hr="1" rbi="1" error="0"></player>
   <player name="William Saavedra D" vb="1" r="0" h="0" double="0" triple="0" hr="0" rbi="0" error="0"></player>
   <player name="Pedro Luis Rodríguez 3B" vb="3" r="1" h="1" double="0" triple="0" hr="1" rbi="1" error="0"></player>
   <player name="Yaser Julio González LF" vb="2" r="0" h="0" double="0" triple="0" hr="0" rbi="0" error="0"></player>
   <player name="Luis Pablo Acosta RF" vb="2" r="0" h="1" double="0" triple="0" hr="0" rbi="0" error="1"></player>
   <player name="Olber Anier Peña C" vb="1" r="0" h="0" double="0" triple="0" hr="0" rbi="0" error="0"></player>
   <player name="Pedro Luis Dueñas 2B" vb="3" r="0" h="0" double="0" triple="0" hr="0" rbi="0" error="1"></player>
   <player name="Yaifredo Domínguez P" vb="0" r="0" h="0" double="0" triple="0" hr="0" rbi="0" error="1"></player>
   <player name="Jenier álvarez P" vb="0" r="0" h="0" double="0" triple="0" hr="0" rbi="0" error="0"></player>
   <player name="Irandi Hernández C" vb="2" r="0" h="1" double="0" triple="0" hr="0" rbi="0" error="0"></player>
   <player name="Frank Raul Gonzalez 1B" vb="1" r="0" h="0" double="0" triple="0" hr="0" rbi="0" error="0"></player>
   <player name="Tony D. Guerra SS" vb="0" r="0" h="0" double="0" triple="0" hr="0" rbi="0" error="0"></player>
   <player name="Geovannys Hernandez LF" vb="1" r="0" h="0" double="0" triple="0" hr="0" rbi="0" error="0"></player>
   <player name="Marlon A. Lamontaña CF" vb="1" r="0" h="0" double="0" triple="0" hr="0" rbi="0" error="0"></player>
   <player name="Frank Carlos Díaz (1),D" vb="1" r="0" h="0" double="0" triple="0" hr="0" rbi="0" error="0"></player>
   <player name="Yosvani Alvarez P" vb="0" r="0" h="0" double="0" triple="0" hr="0" rbi="0" error="0"></player>
  </batters>
  <pitchers>
   <player name="Yaifredo Domínguez" inn="1.0" vb="7" h="5" c="5" cl="4" so="0" bb="2" sb="0"></player>
   <player name="Jenier álvarez" inn="4.0" vb="16" h="3" c="1" cl="0" so="5" bb="2" sb="1"></player>
   <player name="Yosvani Alvarez" inn="1.0" vb="3" h="0" c="0" cl="0" so="1" bb="0" sb="0"></player>
  </pitchers>
 </team>
 <team name="Camaguey" c="6" h="8" e="1">
  <runxining 1="3" 2="3" 3="0" 4="0" 5="0" 6="0" 7=""></runxining>
  <batters>
   <player name="Humberto Bravo 2B" vb="3" r="2" h="1" double="0" triple="0" hr="0" rbi="0" error="0"></player>
   <player name="Yosbel Pérez 3B" vb="3" r="0" h="1" double="0" triple="0" hr="0" rbi="0" error="0"></player>
   <player name="Leonel Segura 1B" vb="1" r="2" h="0" double="0" triple="0" hr="0" rbi="0" error="1"></player>
   <player name="Alexander Ayala SS" vb="4" r="1" h="1" double="1" triple="0" hr="0" rbi="1" error="0"></player>
   <player name="Leslie Anderson D" vb="3" r="0" h="1" double="0" triple="0" hr="0" rbi="1" error="0"></player>
   <player name="Loidel Chapelli LF" vb="3" r="0" h="2" double="0" triple="0" hr="0" rbi="2" error="0"></player>
   <player name="Leonel Moa CF" vb="3" r="0" h="1" double="0" triple="0" hr="0" rbi="0" error="0"></player>
   <player name="Yendri Téllez C" vb="2" r="0" h="0" double="0" triple="0" hr="0" rbi="0" error="0"></player>
   <player name="Luis González RF" vb="2" r="1" h="1" double="1" triple="0" hr="0" rbi="0" error="0"></player>
   <player name="Frank Madan P" vb="0" r="0" h="0" double="0" triple="0" hr="0" rbi="0" error="0"></player>
   <player name="Pedro Smith 1B" vb="1" r="0" h="0" double="0" triple="0" hr="0" rbi="0" error="0"></player>
   <player name="Jorge Cardosa (a)" vb="1" r="0" h="0" double="0" triple="0" hr="0" rbi="0" error="0"></player>
   <player name="Jorge Alvarez C" vb="0" r="0" h="0" double="0" triple="0" hr="0" rbi="0" error="0"></player>
   <player name="Yanmichel Flores LF" vb="0" r="0" h="0" double="0" triple="0" hr="0" rbi="0" error="0"></player>
   <player name="Yandy Yanes 2B" vb="0" r="0" h="0" double="0" triple="0" hr="0" rbi="0" error="0"></player>
  </batters>
  <pitchers>
   <player name="Frank Madan" inn="7.0" vb="26" h="4" c="2" cl="2" so="3" bb="0" sb="1"></player>
  </pitchers>
 </team>
 <pronostico>
  <voto name="A favor de Camaguey" valor="61"></voto>
  <voto name="A favor de Pinar del Rio" valor="53"></voto>
 </pronostico>
</game>